{
  "service": {
    "service": "imove-reportes-ercot-role",
    "serviceObject": {
      "name": "imove-reportes-ercot-role"
    },
    "provider": {
      "name": "aws",
      "runtime": "python3.12",
      "stage": "dev",
      "region": "us-east-1",
      "environment": {
        "REGION": "us-east-1"
      },
      "versionFunctions": true,
      "compiledCloudFormationTemplate": {
        "AWSTemplateFormatVersion": "2010-09-09",
        "Description": "The AWS CloudFormation template for this Serverless application",
        "Resources": {
          "ReportesErcotRole": {
            "Type": "AWS::IAM::Role",
            "Properties": {
              "RoleName": "ReportesErcotRole",
              "MaxSessionDuration": 3600,
              "AssumeRolePolicyDocument": {
                "Statement": [
                  {
                    "Effect": "Allow",
                    "Principal": {
                      "Service": "lambda.amazonaws.com"
                    },
                    "Action": [
                      "sts:AssumeRole"
                    ]
                  }
                ]
              },
              "ManagedPolicyArns": [
                "arn:aws:iam::aws:policy/service-role/AWSLambdaBasicExecutionRole",
                {
                  "Ref": "S3ErcotReportsPolicy"
                },
                {
                  "Ref": "SecretsErcotReportsPolicy"
                },
                {
                  "Ref": "LayersErcotReportsPolicy"
                }
              ]
            }
          },
          "S3ErcotReportsPolicy": {
            "Type": "AWS::IAM::ManagedPolicy",
            "Properties": {
              "ManagedPolicyName": "S3ErcotReportsPolicy",
              "Description": "Lambda policy to allow access to s3 api info",
              "Path": "/",
              "PolicyDocument": {
                "Version": "2012-10-17",
                "Statement": [
                  {
                    "Effect": "Allow",
                    "Action": [
                      "s3:GetObject"
                    ],
                    "Resource": [
                      "arn:aws:s3:::medidores-ercot-dev",
                      "arn:aws:s3:::medidores-ercot-dev/*"
                    ]
                  }
                ]
              }
            }
          },
          "SecretsErcotReportsPolicy": {
            "Type": "AWS::IAM::ManagedPolicy",
            "Properties": {
              "ManagedPolicyName": "SecretsErcotReportsPolicy",
              "Description": "Lambda policy to allow access to secrets manager apan model",
              "Path": "/",
              "PolicyDocument": {
                "Version": "2012-10-17",
                "Statement": [
                  {
                    "Effect": "Allow",
                    "Action": [
                      "secretsmanager:GetSecretValue"
                    ],
                    "Resource": [
                      "arn:aws:secretsmanager:us-east-1:857285351963:secret:dev/energrid/db-VJsD0e"
                    ]
                  }
                ]
              }
            }
          },
          "LayersErcotReportsPolicy": {
            "Type": "AWS::IAM::ManagedPolicy",
            "Properties": {
              "ManagedPolicyName": "LayersErcotReportsPolicy",
              "Description": "Lambda policy to allow access to secrets manager apan model",
              "Path": "/",
              "PolicyDocument": {
                "Version": "2012-10-17",
                "Statement": [
                  {
                    "Effect": "Allow",
                    "Action": [
                      "lambda:GetLayerVersion"
                    ],
                    "Resource": [
                      "*"
                    ]
                  }
                ]
              }
            }
          }
        },
        "Outputs": {
          "ServerlessDeploymentBucketName": {
            "Value": "serverless-framework-deployments-us-east-1-5804d545-76c0",
            "Export": {
              "Name": "sls-imove-reportes-ercot-role-dev-ServerlessDeploymentBucketName"
            }
          }
        }
      }
    },
    "custom": {
      "stage": "dev",
      "my-region": "us-east-1",
      "config": {
        "prod": {
          "account_id": "857285351963"
        },
        "dev": {
          "account_id": "857285351963"
        }
      }
    },
    "pluginsData": {},
    "functions": {},
    "resources": {
      "Resources": {
        "ReportesErcotRole": {
          "Type": "AWS::IAM::Role",
          "Properties": {
            "RoleName": "ReportesErcotRole",
            "MaxSessionDuration": 3600,
            "AssumeRolePolicyDocument": {
              "Statement": [
                {
                  "Effect": "Allow",
                  "Principal": {
                    "Service": "lambda.amazonaws.com"
                  },
                  "Action": [
                    "sts:AssumeRole"
                  ]
                }
              ]
            },
            "ManagedPolicyArns": [
              "arn:aws:iam::aws:policy/service-role/AWSLambdaBasicExecutionRole",
              {
                "Ref": "S3ErcotReportsPolicy"
              },
              {
                "Ref": "SecretsErcotReportsPolicy"
              },
              {
                "Ref": "LayersErcotReportsPolicy"
              }
            ]
          }
        },
        "S3ErcotReportsPolicy": {
          "Type": "AWS::IAM::ManagedPolicy",
          "Properties": {
            "ManagedPolicyName": "S3ErcotReportsPolicy",
            "Description": "Lambda policy to allow access to s3 api info",
            "Path": "/",
            "PolicyDocument": {
              "Version": "2012-10-17",
              "Statement": [
                {
                  "Effect": "Allow",
                  "Action": [
                    "s3:GetObject"
                  ],
                  "Resource": [
                    "arn:aws:s3:::medidores-ercot-dev",
                    "arn:aws:s3:::medidores-ercot-dev/*"
                  ]
                }
              ]
            }
          }
        },
        "SecretsErcotReportsPolicy": {
          "Type": "AWS::IAM::ManagedPolicy",
          "Properties": {
            "ManagedPolicyName": "SecretsErcotReportsPolicy",
            "Description": "Lambda policy to allow access to secrets manager apan model",
            "Path": "/",
            "PolicyDocument": {
              "Version": "2012-10-17",
              "Statement": [
                {
                  "Effect": "Allow",
                  "Action": [
                    "secretsmanager:GetSecretValue"
                  ],
                  "Resource": [
                    "arn:aws:secretsmanager:us-east-1:857285351963:secret:dev/energrid/db-VJsD0e"
                  ]
                }
              ]
            }
          }
        },
        "LayersErcotReportsPolicy": {
          "Type": "AWS::IAM::ManagedPolicy",
          "Properties": {
            "ManagedPolicyName": "LayersErcotReportsPolicy",
            "Description": "Lambda policy to allow access to secrets manager apan model",
            "Path": "/",
            "PolicyDocument": {
              "Version": "2012-10-17",
              "Statement": [
                {
                  "Effect": "Allow",
                  "Action": [
                    "lambda:GetLayerVersion"
                  ],
                  "Resource": [
                    "*"
                  ]
                }
              ]
            }
          }
        }
      },
      "Outputs": {}
    },
    "configValidationMode": "warn",
    "serviceFilename": "serverless",
    "initialServerlessConfig": {
      "service": "imove-reportes-ercot-role",
      "provider": {
        "$ref": "$[\"service\"][\"provider\"]"
      },
      "custom": {
        "$ref": "$[\"service\"][\"custom\"]"
      },
      "resources": {
        "$ref": "$[\"service\"][\"resources\"]"
      }
    },
    "appId": null,
    "orgId": null,
    "layers": {}
  },
  "package": {
    "artifactDirectoryName": "serverless/imove-reportes-ercot-role/dev/1762366121303-2025-11-05T18:08:41.303Z",
    "artifact": ""
  }
}